coollogs/__init__.py
coollogs/logger.py
coollogs-0.3.0.dist-info/LICENSE
coollogs-0.3.0.dist-info/METADATA
coollogs-0.3.0.dist-info/WHEEL
coollogs-0.3.0.dist-info/top_level.txt
coollogs-0.3.0.dist-info/RECORD
