Metadata-Version: 2.1
Name: coollogs
Version: 0.3.0
Summary: Simple output beautifier for python 3
Home-page: https://github.com/LeKSuS-04/Cool-logs
Author: Alexey Tarasov
Author-email: tarasovion2004@gmail.com
License: GNU GPLv3
Platform: UNKNOWN
License-File: LICENSE
